qrand/__init__.py
qrand/_qiskit_bit_generator.py
qrand/caches/__init__.py
qrand/caches/basic.py
qrand/caches/cache.py
qrand/errors/__init__.py
qrand/errors/development.py
qrand/helpers/__init__.py
qrand/helpers/argument_validation.py
qrand/helpers/bounded_factorization.py
qrand/helpers/numeral_encodings.py
qrand/platforms/__init__.py
qrand/platforms/backend.py
qrand/platforms/circuit.py
qrand/platforms/cirq/__init__.py
qrand/platforms/cirq/backend.py
qrand/platforms/cirq/circuit.py
qrand/platforms/cirq/job.py
qrand/platforms/cirq/platform.py
qrand/platforms/factory.py
qrand/platforms/job.py
qrand/platforms/platform.py
qrand/platforms/qiskit/__init__.py
qrand/platforms/qiskit/backend.py
qrand/platforms/qiskit/circuit.py
qrand/platforms/qiskit/job.py
qrand/platforms/qiskit/platform.py
qrand/platforms/qsharp/__init__.py
qrand/platforms/qsharp/backend.py
qrand/platforms/qsharp/circuit.py
qrand/platforms/qsharp/job.py
qrand/platforms/qsharp/platform.py
qrand/protocols/__init__.py
qrand/protocols/entanglement.py
qrand/protocols/hadamard.py
qrand/protocols/protocol.py
qrand/protocols/result.py
qrand/protocols/sycamore.py
qrand/qrng.py
qrand/qrngV1.py
qrand/quantum_bit_generator.py
qrand/validation/__init__.py
qrand/validation/block_frequency.py
qrand/validation/monobit_frequency.py
qrand/validation/runs.py
qrand/validation/validation.py
qrand-0.4.0.dist-info/LICENSE
qrand-0.4.0.dist-info/WHEEL
qrand-0.4.0.dist-info/METADATA
qrand-0.4.0.dist-info/RECORD
