Metadata-Version: 2.1
Name: qrand
Version: 0.4.0
Summary: A multiprotocol and multiplatform quantum random number generation framework
Home-page: https://github.com/pedrorrivero/qrand
License: Apache-2.0
Author: Pedro Rivero
Author-email: pedro.rivero.ramirez@gmail.com
Requires-Python: >=3.9,<4.0
Classifier: License :: OSI Approved :: Apache Software License
Classifier: Programming Language :: Python :: 3
Classifier: Programming Language :: Python :: 3.9
Provides-Extra: cirq
Provides-Extra: qiskit
Provides-Extra: qsharp
Requires-Dist: cirq (>=0.10.0,<0.11.0); extra == "cirq"
Requires-Dist: numpy (>=1.19.4,<2.0.0)
Requires-Dist: qiskit-aer (>=0.8.2,<0.9.0); extra == "qiskit"
Requires-Dist: qiskit-ibmq-provider (==0.12.3); extra == "qiskit"
Requires-Dist: qiskit-terra (>=0.17.2,<0.18.0); extra == "qiskit"
Requires-Dist: qsharp (>=0.15.2103,<0.16.0); extra == "qsharp"
Requires-Dist: randomgen (>=1.19.3,<2.0.0)
